aiohttp_fast_url_dispatcher/__init__.py
aiohttp_fast_url_dispatcher/py.typed
aiohttp_fast_url_dispatcher-0.3.1.dist-info/LICENSE
aiohttp_fast_url_dispatcher-0.3.1.dist-info/METADATA
aiohttp_fast_url_dispatcher-0.3.1.dist-info/WHEEL
aiohttp_fast_url_dispatcher-0.3.1.dist-info/RECORD
