Metadata-Version: 2.1
Name: aiohttp-fast-url-dispatcher
Version: 0.3.1
Summary: A faster URL dispatcher for aiohttp
Home-page: https://github.com/bdraco/aiohttp-fast-url-dispatcher
Author: J. Nick Koston
Author-email: nick@koston.org
Requires-Python: >=3.8,<4.0
Classifier: Development Status :: 2 - Pre-Alpha
Classifier: Intended Audience :: Developers
Classifier: License :: OSI Approved :: Apache Software License
Classifier: Natural Language :: English
Classifier: Operating System :: OS Independent
Classifier: Programming Language :: Python :: 3
Classifier: Programming Language :: Python :: 3.8
Classifier: Programming Language :: Python :: 3.9
Classifier: Programming Language :: Python :: 3.10
Classifier: Programming Language :: Python :: 3.11
Classifier: Programming Language :: Python :: 3.12
Classifier: Topic :: Software Development :: Libraries
Requires-Dist: aiohttp (>=3.8.5,<3.10)
Project-URL: Bug Tracker, https://github.com/bdraco/aiohttp-fast-url-dispatcher/issues
Project-URL: Changelog, https://github.com/bdraco/aiohttp-fast-url-dispatcher/blob/main/CHANGELOG.md
Project-URL: Documentation, https://aiohttp-fast-url-dispatcher.readthedocs.io
Project-URL: Repository, https://github.com/bdraco/aiohttp-fast-url-dispatcher
